pyrs990/__init__.py
pyrs990/__main__.py
pyrs990/_config.py
pyrs990/_options.py
pyrs990/annual_record.py
pyrs990/app.py
pyrs990/bmf_record.py
pyrs990/cache.py
pyrs990/constants.py
pyrs990/downloader.py
pyrs990/entry_point.py
pyrs990/filing.py
pyrs990/filters.py
pyrs990/formatter.py
pyrs990/index.py
pyrs990/querier.py
pyrs990/result.py
pyrs990/types.py
pyrs990/version.txt
pyrs990-0.1.4.dist-info/entry_points.txt
pyrs990-0.1.4.dist-info/WHEEL
pyrs990-0.1.4.dist-info/METADATA
pyrs990-0.1.4.dist-info/RECORD
