Metadata-Version: 2.1
Name: pyrs990
Version: 0.1.4
Summary: A tool for fetching and filtering IRS 990 data.
Home-page: https://github.com/code-for-montana/pyrs990
License: GPL-3.0
Keywords: open data,irs,irs 990,etl
Author: George Lesica
Author-email: george@lesica.com
Requires-Python: >=3.8,<4.0
Classifier: Development Status :: 3 - Alpha
Classifier: Environment :: Console
Classifier: Intended Audience :: Developers
Classifier: Intended Audience :: Other Audience
Classifier: License :: OSI Approved :: GNU General Public License v3 (GPLv3)
Classifier: Natural Language :: English
Classifier: Programming Language :: Python :: 3
Classifier: Programming Language :: Python :: 3.8
Classifier: Topic :: Text Processing :: Markup :: XML
Classifier: Typing :: Typed
Requires-Dist: defusedxml (>=0.6.0,<0.7.0)
Requires-Dist: requests (>=2.23.0,<3.0.0)
Project-URL: Repository, https://github.com/code-for-montana/pyrs990
